oemof/visio/__init__.py
oemof/visio/energy_system_graph.py
oemof/visio/plot.py
oemof_visio-0.0.2.dist-info/licenses/LICENSE
oemof_visio-0.0.2.dist-info/WHEEL
oemof_visio-0.0.2.dist-info/METADATA
oemof_visio-0.0.2.dist-info/RECORD
