Metadata-Version: 2.4
Name: oemof.visio
Version: 0.0.2
Summary: A package that contains postprocessing and visualisation tools for oemof-solph models
Author-email: oemof developing group <contact@oemof.org>
Requires-Python: >=3.10
License-Expression: MIT
Classifier: Programming Language :: Python :: 3
Classifier: Operating System :: OS Independent
Classifier: Development Status :: 3 - Alpha
License-File: LICENSE
Requires-Dist: matplotlib
Requires-Dist: pandas
Requires-Dist: plotly
Requires-Dist: graphviz ; extra == "network"
Requires-Dist: oemof.network ; extra == "network"
Project-URL: Homepage, https://github.com/oemof/oemof-visio
Project-URL: Issues, https://github.com/oemof/oemof-visio/issues
Provides-Extra: network
